llm_agents/__init__.py
llm_agents/agent.py
llm_agents/llm.py
llm_agents-0.0.2.dist-info/LICENSE
llm_agents-0.0.2.dist-info/METADATA
llm_agents-0.0.2.dist-info/WHEEL
llm_agents-0.0.2.dist-info/top_level.txt
llm_agents-0.0.2.dist-info/RECORD
