Metadata-Version: 2.1
Name: llm-agents
Version: 0.0.2
Summary: llm_agents
Home-page: https://github.com/mpaepper/llm_agents
Author: Marc Päpper
Author-email: mpaepper <mpaepper@gmx.de>
Classifier: Programming Language :: Python :: 3
Classifier: License :: OSI Approved :: MIT License
Classifier: Operating System :: OS Independent
Requires-Python: >=3.7
License-File: LICENSE
Requires-Dist: google-search-results (>=2.4.2)
Requires-Dist: openai (>=0.27.0)
Requires-Dist: pydantic (>=1.10.5)
Requires-Dist: requests (>=2.28.2)
